kuromi/__init__.py
kuromi/cli/__init__.py
kuromi/cli/main.py
kuromi/cli/run.py
kuromi-0.0.2.dist-info/METADATA
kuromi-0.0.2.dist-info/WHEEL
kuromi-0.0.2.dist-info/entry_points.txt
kuromi-0.0.2.dist-info/top_level.txt
kuromi-0.0.2.dist-info/zip-safe
kuromi-0.0.2.dist-info/RECORD
